[{"w": "a2 Milk Lactose Free Full Cream 2L", "c": "Farmhouse Gold Full Cream Milk"}, {"w": "a2 Milk Lactose Free Full Cream 2L", "c": "Zymil Lactose Free Full Cream Milk"}, {"w": "a2 Milk Lactose Free Full Cream 2L", "c": "Australian Full Cream Long Life Milk"}, {"w": "a2 Milk Lactose Free Full Cream 2L", "c": "Lactose Free Long Life Full Cream Milk"}, {"w": "a2 Milk Lactose Free Full Cream 2L", "c": "Lactose Free Full Cream Milk"}, {"w": "a2 Milk Lactose Free Full Cream 2L", "c": "Lactose Free Uht Milk Low Fat"}, {"w": "a2 Milk Lactose Free Full Cream 2L", "c": "Full Cream Milk"}, {"w": "a2 Milk Lactose Free Full Cream 2L", "c": "Dairy Full Cream Milk"}, {"w": "a2 Milk Lactose Free Full Cream 2L", "c": "Smarter White Milk 2% Fat Full Cream Taste"}, {"w": "a2 Milk Lactose Free Full Cream 2L", "c": "Fresh Full Cream Milk"}, {"w": "a2 Milk Lactose Free Full Cream 2L", "c": "Zymil Lactose Free Low Fat Milk"}, {"w": "a2 Milk Lactose Free Full Cream 2L", "c": "Full Cream Long Life Milk"}, {"w": "Reese's Peanut Butter Cups Miniatures Milk Chocolate 150g", "c": "Dairy Milk Block Chocolate"}, {"w": "Reese's Peanut Butter Cups Miniatures Milk Chocolate 150g", "c": "Peanut Butter Cups Milk Chocolate 2 pack"}, {"w": "Reese's Peanut Butter Cups Miniatures Milk Chocolate 150g", "c": "Kit Kat Chocolate Milk 4 Finger Bar"}, {"w": "Riverina Fresh Full Cream Milk 2L", "c": "Farmhouse Gold Full Cream Milk"}, {"w": "Riverina Fresh Full Cream Milk 2L", "c": "Zymil Lactose Free Full Cream Milk"}, {"w": "Riverina Fresh Full Cream Milk 2L", "c": "Australian Full Cream Long Life Milk"}, {"w": "Riverina Fresh Full Cream Milk 2L", "c": "Lactose Free Long Life Full Cream Milk"}, {"w": "Riverina Fresh Full Cream Milk 2L", "c": "Lactose Free Full Cream Milk"}, {"w": "Riverina Fresh Full Cream Milk 2L", "c": "Full Cream Milk"}, {"w": "Riverina Fresh Full Cream Milk 2L", "c": "Dairy Full Cream Milk"}, {"w": "Riverina Fresh Full Cream Milk 2L", "c": "Smarter White Milk 2% Fat Full Cream Taste"}, {"w": "Riverina Fresh Full Cream Milk 2L", "c": "Fresh Full Cream Milk"}, {"w": "Riverina Fresh Full Cream Milk 2L", "c": "Full Cream Long Life Milk"}, {"w": "Riverina Fresh Lactose Free Full Cream Milk 2L", "c": "Farmhouse Gold Full Cream Milk"}, {"w": "Riverina Fresh Lactose Free Full Cream Milk 2L", "c": "Zymil Lactose Free Full Cream Milk"}, {"w": "Riverina Fresh Lactose Free Full Cream Milk 2L", "c": "Australian Full Cream Long Life Milk"}, {"w": "Riverina Fresh Lactose Free Full Cream Milk 2L", "c": "Lactose Free Long Life Full Cream Milk"}, {"w": "Riverina Fresh Lactose Free Full Cream Milk 2L", "c": "Lactose Free Full Cream Milk"}, {"w": "Riverina Fresh Lactose Free Full Cream Milk 2L", "c": "Lactose Free Uht Milk Low Fat"}, {"w": "Riverina Fresh Lactose Free Full Cream Milk 2L", "c": "Full Cream Milk"}, {"w": "Riverina Fresh Lactose Free Full Cream Milk 2L", "c": "Dairy Full Cream Milk"}, {"w": "Riverina Fresh Lactose Free Full Cream Milk 2L", "c": "Smarter White Milk 2% Fat Full Cream Taste"}, {"w": "Riverina Fresh Lactose Free Full Cream Milk 2L", "c": "Fresh Full Cream Milk"}, {"w": "Riverina Fresh Lactose Free Full Cream Milk 2L", "c": "Zymil Lactose Free Low Fat Milk"}, {"w": "Riverina Fresh Lactose Free Full Cream Milk 2L", "c": "Full Cream Long Life Milk"}, {"w": "a2 Milk Lactose Free Full Cream 1L", "c": "Farmhouse Gold Full Cream Milk"}, {"w": "a2 Milk Lactose Free Full Cream 1L", "c": "Zymil Lactose Free Full Cream Milk"}, {"w": "a2 Milk Lactose Free Full Cream 1L", "c": "Australian Full Cream Long Life Milk"}, {"w": "a2 Milk Lactose Free Full Cream 1L", "c": "Lactose Free Long Life Full Cream Milk"}, {"w": "a2 Milk Lactose Free Full Cream 1L", "c": "Lactose Free Full Cream Milk"}, {"w": "a2 Milk Lactose Free Full Cream 1L", "c": "Lactose Free Uht Milk Low Fat"}, {"w": "a2 Milk Lactose Free Full Cream 1L", "c": "Calci-Plus Long Life Soy Milk 1L"}, {"w": "a2 Milk Lactose Free Full Cream 1L", "c": "Full Cream Milk"}, {"w": "a2 Milk Lactose Free Full Cream 1L", "c": "Dairy Full Cream Milk"}, {"w": "a2 Milk Lactose Free Full Cream 1L", "c": "Smarter White Milk 2% Fat Full Cream Taste"}, {"w": "a2 Milk Lactose Free Full Cream 1L", "c": "Fresh Full Cream Milk"}, {"w": "a2 Milk Lactose Free Full Cream 1L", "c": "Zymil Lactose Free Low Fat Milk"}, {"w": "a2 Milk Lactose Free Full Cream 1L", "c": "Full Cream Long Life Milk"}, {"w": "Woolworths Free From Lactose Milk Full Cream 2L", "c": "Farmhouse Gold Full Cream Milk"}, {"w": "Woolworths Free From Lactose Milk Full Cream 2L", "c": "Zymil Lactose Free Full Cream Milk"}, {"w": "Woolworths Free From Lactose Milk Full Cream 2L", "c": "Australian Full Cream Long Life Milk"}, {"w": "Woolworths Free From Lactose Milk Full Cream 2L", "c": "Lactose Free Long Life Full Cream Milk"}, {"w": "Woolworths Free From Lactose Milk Full Cream 2L", "c": "Lactose Free Full Cream Milk"}, {"w": "Woolworths Free From Lactose Milk Full Cream 2L", "c": "Lactose Free Uht Milk Low Fat"}, {"w": "Woolworths Free From Lactose Milk Full Cream 2L", "c": "Full Cream Milk"}, {"w": "Woolworths Free From Lactose Milk Full Cream 2L", "c": "Dairy Full Cream Milk"}, {"w": "Woolworths Free From Lactose Milk Full Cream 2L", "c": "Smarter White Milk 2% Fat Full Cream Taste"}, {"w": "Woolworths Free From Lactose Milk Full Cream 2L", "c": "Fresh Full Cream Milk"}, {"w": "Woolworths Free From Lactose Milk Full Cream 2L", "c": "Zymil Lactose Free Low Fat Milk"}, {"w": "Woolworths Free From Lactose Milk Full Cream 2L", "c": "Full Cream Long Life Milk"}, {"w": "KitKat Milk Chocolate Mini Bars 11 pack", "c": "Dairy Milk Block Chocolate"}, {"w": "KitKat Milk Chocolate Mini Bars 11 pack", "c": "Peanut Butter Cups Milk Chocolate 2 pack"}, {"w": "KitKat Milk Chocolate Mini Bars 11 pack", "c": "Kit Kat Chocolate Milk 4 Finger Bar"}, {"w": "Woolworths Milk Chocolate Almonds 190g", "c": "Dairy Milk Block Chocolate"}, {"w": "Woolworths Milk Chocolate Almonds 190g", "c": "Peanut Butter Cups Milk Chocolate 2 pack"}, {"w": "Woolworths Milk Chocolate Almonds 190g", "c": "Kit Kat Chocolate Milk 4 Finger Bar"}, {"w": "Cadbury Dairy Milk Chocolate Share Mini Bars 12 pack 144g", "c": "Dairy Milk Block Chocolate"}, {"w": "Cadbury Dairy Milk Chocolate Share Mini Bars 12 pack 144g", "c": "Peanut Butter Cups Milk Chocolate 2 pack"}, {"w": "Cadbury Dairy Milk Chocolate Share Mini Bars 12 pack 144g", "c": "Kit Kat Chocolate Milk 4 Finger Bar"}, {"w": "Cadbury Dairy Milk Chocolate Share Mini Bars 12 pack 144g", "c": "Dairy Full Cream Milk"}, {"w": "a2 Milk Full Cream 3L", "c": "Farmhouse Gold Full Cream Milk"}, {"w": "a2 Milk Full Cream 3L", "c": "Zymil Lactose Free Full Cream Milk"}, {"w": "a2 Milk Full Cream 3L", "c": "Australian Full Cream Long Life Milk"}, {"w": "a2 Milk Full Cream 3L", "c": "Lactose Free Long Life Full Cream Milk"}, {"w": "a2 Milk Full Cream 3L", "c": "Lactose Free Full Cream Milk"}, {"w": "a2 Milk Full Cream 3L", "c": "Full Cream Milk"}, {"w": "a2 Milk Full Cream 3L", "c": "Dairy Full Cream Milk"}, {"w": "a2 Milk Full Cream 3L", "c": "Smarter White Milk 2% Fat Full Cream Taste"}, {"w": "a2 Milk Full Cream 3L", "c": "Fresh Full Cream Milk"}, {"w": "a2 Milk Full Cream 3L", "c": "Full Cream Long Life Milk"}, {"w": "Hunter Belle Dairy Co Full Cream Milk Unhomogenised 2L", "c": "Farmhouse Gold Full Cream Milk"}, {"w": "Hunter Belle Dairy Co Full Cream Milk Unhomogenised 2L", "c": "Zymil Lactose Free Full Cream Milk"}, {"w": "Hunter Belle Dairy Co Full Cream Milk Unhomogenised 2L", "c": "Australian Full Cream Long Life Milk"}, {"w": "Hunter Belle Dairy Co Full Cream Milk Unhomogenised 2L", "c": "Dairy Milk Block Chocolate"}, {"w": "Hunter Belle Dairy Co Full Cream Milk Unhomogenised 2L", "c": "Lactose Free Long Life Full Cream Milk"}, {"w": "Hunter Belle Dairy Co Full Cream Milk Unhomogenised 2L", "c": "Lactose Free Full Cream Milk"}, {"w": "Hunter Belle Dairy Co Full Cream Milk Unhomogenised 2L", "c": "Full Cream Milk"}, {"w": "Hunter Belle Dairy Co Full Cream Milk Unhomogenised 2L", "c": "Dairy Full Cream Milk"}, {"w": "Hunter Belle Dairy Co Full Cream Milk Unhomogenised 2L", "c": "Smarter White Milk 2% Fat Full Cream Taste"}, {"w": "Hunter Belle Dairy Co Full Cream Milk Unhomogenised 2L", "c": "Fresh Full Cream Milk"}, {"w": "Hunter Belle Dairy Co Full Cream Milk Unhomogenised 2L", "c": "Full Cream Long Life Milk"}, {"w": "Pauls Smarter White Low Fat Milk 1L", "c": "Lite Reduced Fat Milk"}, {"w": "Pauls Smarter White Low Fat Milk 1L", "c": "Lactose Free Uht Milk Low Fat"}, {"w": "Pauls Smarter White Low Fat Milk 1L", "c": "Calci-Plus Long Life Soy Milk 1L"}, {"w": "Pauls Smarter White Low Fat Milk 1L", "c": "Smarter White Milk 2% Fat Full Cream Taste"}, {"w": "Pauls Smarter White Low Fat Milk 1L", "c": "Zymil Lactose Free Low Fat Milk"}, {"w": "Cadbury Dairy Milk Chocolate Caramello Koala 12 pack 180g", "c": "Dairy Milk Block Chocolate"}, {"w": "Cadbury Dairy Milk Chocolate Caramello Koala 12 pack 180g", "c": "Peanut Butter Cups Milk Chocolate 2 pack"}, {"w": "Cadbury Dairy Milk Chocolate Caramello Koala 12 pack 180g", "c": "Kit Kat Chocolate Milk 4 Finger Bar"}, {"w": "Cadbury Dairy Milk Chocolate Caramello Koala 12 pack 180g", "c": "Dairy Full Cream Milk"}, {"w": "The Complete Dairy Full Cream Milk 1L", "c": "Farmhouse Gold Full Cream Milk"}, {"w": "The Complete Dairy Full Cream Milk 1L", "c": "Zymil Lactose Free Full Cream Milk"}, {"w": "The Complete Dairy Full Cream Milk 1L", "c": "Australian Full Cream Long Life Milk"}, {"w": "The Complete Dairy Full Cream Milk 1L", "c": "Dairy Milk Block Chocolate"}, {"w": "The Complete Dairy Full Cream Milk 1L", "c": "Lactose Free Long Life Full Cream Milk"}, {"w": "The Complete Dairy Full Cream Milk 1L", "c": "Lactose Free Full Cream Milk"}, {"w": "The Complete Dairy Full Cream Milk 1L", "c": "Calci-Plus Long Life Soy Milk 1L"}, {"w": "The Complete Dairy Full Cream Milk 1L", "c": "Full Cream Milk"}, {"w": "The Complete Dairy Full Cream Milk 1L", "c": "Dairy Full Cream Milk"}, {"w": "The Complete Dairy Full Cream Milk 1L", "c": "Smarter White Milk 2% Fat Full Cream Taste"}, {"w": "The Complete Dairy Full Cream Milk 1L", "c": "Fresh Full Cream Milk"}, {"w": "The Complete Dairy Full Cream Milk 1L", "c": "Full Cream Long Life Milk"}]